mealsearchpy/__init__.py
mealsearchpy/mealsearchpy.py
mealsearchpy-0.1.2.dist-info/LICENSE
mealsearchpy-0.1.2.dist-info/WHEEL
mealsearchpy-0.1.2.dist-info/METADATA
mealsearchpy-0.1.2.dist-info/RECORD
