Metadata-Version: 2.1
Name: mealsearchpy
Version: 0.1.2
Summary: A Python package for people to find their favourite recipes.
Home-page: https://github.com/QMSS-G5072-2022/Dai_Anni/tree/main/Final_Project/mealsearchpy
License: MIT
Author: Anni Dai
Requires-Python: >=3.9,<4.0
Classifier: License :: OSI Approved :: MIT License
Classifier: Programming Language :: Python :: 3
Classifier: Programming Language :: Python :: 3.9
Classifier: Programming Language :: Python :: 3.10
Requires-Dist: pandas (>=1.5.2,<2.0.0)
Requires-Dist: requests (>=2.28.1,<3.0.0)
Project-URL: Repository, https://github.com/QMSS-G5072-2022/Dai_Anni/tree/main/Final_Project/mealsearchpy
